{"nodes": [{"id": "c_users_base_desktop_seb_pandora_scratch_test_vol_match_py", "label": "test_vol_match.py", "file_type": "code", "source_file": "scratch/test_vol_match.py", "source_location": "L1"}, {"id": "scratch_test_vol_match_test_matching", "label": "test_matching()", "file_type": "code", "source_file": "scratch/test_vol_match.py", "source_location": "L4"}], "edges": [{"source": "c_users_base_desktop_seb_pandora_scratch_test_vol_match_py", "target": "pycaw_pycaw", "relation": "imports_from", "context": "import", "confidence": "EXTRACTED", "source_file": "scratch/test_vol_match.py", "source_location": "L1", "weight": 1.0}, {"source": "c_users_base_desktop_seb_pandora_scratch_test_vol_match_py", "target": "pythoncom", "relation": "imports", "context": "import", "confidence": "EXTRACTED", "source_file": "scratch/test_vol_match.py", "source_location": "L2", "weight": 1.0}, {"source": "c_users_base_desktop_seb_pandora_scratch_test_vol_match_py", "target": "scratch_test_vol_match_test_matching", "relation": "contains", "confidence": "EXTRACTED", "source_file": "scratch/test_vol_match.py", "source_location": "L4", "weight": 1.0}], "raw_calls": [{"caller_nid": "scratch_test_vol_match_test_matching", "callee": "CoInitialize", "is_member_call": true, "source_file": "C:\\Users\\Base\\Desktop\\Seb\\Pandora\\scratch\\test_vol_match.py", "source_location": "L5"}, {"caller_nid": "scratch_test_vol_match_test_matching", "callee": "GetAllSessions", "is_member_call": true, "source_file": "C:\\Users\\Base\\Desktop\\Seb\\Pandora\\scratch\\test_vol_match.py", "source_location": "L6"}, {"caller_nid": "scratch_test_vol_match_test_matching", "callee": "lower", "is_member_call": true, "source_file": "C:\\Users\\Base\\Desktop\\Seb\\Pandora\\scratch\\test_vol_match.py", "source_location": "L12"}, {"caller_nid": "scratch_test_vol_match_test_matching", "callee": "name", "is_member_call": true, "source_file": "C:\\Users\\Base\\Desktop\\Seb\\Pandora\\scratch\\test_vol_match.py", "source_location": "L12"}, {"caller_nid": "scratch_test_vol_match_test_matching", "callee": "lower", "is_member_call": true, "source_file": "C:\\Users\\Base\\Desktop\\Seb\\Pandora\\scratch\\test_vol_match.py", "source_location": "L13"}, {"caller_nid": "scratch_test_vol_match_test_matching", "callee": "lower", "is_member_call": true, "source_file": "C:\\Users\\Base\\Desktop\\Seb\\Pandora\\scratch\\test_vol_match.py", "source_location": "L13"}, {"caller_nid": "scratch_test_vol_match_test_matching", "callee": "replace", "is_member_call": true, "source_file": "C:\\Users\\Base\\Desktop\\Seb\\Pandora\\scratch\\test_vol_match.py", "source_location": "L17"}, {"caller_nid": "scratch_test_vol_match_test_matching", "callee": "lower", "is_member_call": true, "source_file": "C:\\Users\\Base\\Desktop\\Seb\\Pandora\\scratch\\test_vol_match.py", "source_location": "L18"}, {"caller_nid": "scratch_test_vol_match_test_matching", "callee": "lower", "is_member_call": true, "source_file": "C:\\Users\\Base\\Desktop\\Seb\\Pandora\\scratch\\test_vol_match.py", "source_location": "L18"}]}